[
    {
        "title": "Giới thiệu",
        "type": "leaf",
        "content": "Bánh cáy là một loại bánh truyền thống của làng Nguyễn, thuộc xã Nguyên Xá, huyện Đông Hưng, tỉnh Thái Bình. Loại bánh này được làm từ các nguyên liệu như gạo nếp, lạc, vừng, gấc, mỡ lợn, vỏ quýt và được chế biến qua nhiều quy trình phức tạp. Tên gọi của bánh cáy bắt nguồn từ hạt nếp cái hoa vàng đem ngâm, trộn gấc đỏ đồ xôi, rồi ép dẻo, xắt hạt lựu lại đem phơi khô, có màu vàng giống trứng con cáy. Bánh cáy là một thức quà quê bình dị, vừa béo, vừa bùi, với độ ngọt vừa phải, thơm mùi lạc, vừng rang, ngậy vị của mứt bí, độ béo của xôi, dừa và vị cay cay của gừng. Để làm được một mẻ bánh cáy, người dân phải trải qua nhiều công đoạn tỉ mỉ, từ việc sơ chế nguyên liệu đến việc trộn và tạo hình bánh. Hiện nay, toàn xã Nguyên Xá có khoảng 300 hộ làm bánh, cho sản lượng 120-150 tấn mỗi tháng, và bánh cáy đã trở thành một đặc sản nổi tiếng của tỉnh Thái Bình.",
        "source": [
            1,
            2,
            3,
            4,
            5
        ],
        "children": []
    }
]